pl_viz/__init__.py
pl_viz/pl_api.py
pl_viz/utils.py
pl_viz-0.4.0.dist-info/LICENSE
pl_viz-0.4.0.dist-info/METADATA
pl_viz-0.4.0.dist-info/WHEEL
pl_viz-0.4.0.dist-info/RECORD
