Metadata-Version: 2.3
Name: pl_viz
Version: 0.4.0
Summary: Fetch and visualize data from PL.
License: MIT
Author: Ben Chen
Requires-Python: >=3.10
Classifier: License :: OSI Approved :: MIT License
Classifier: Programming Language :: Python :: 3
Classifier: Programming Language :: Python :: 3.10
Classifier: Programming Language :: Python :: 3.11
Classifier: Programming Language :: Python :: 3.12
Classifier: Programming Language :: Python :: 3.13
Requires-Dist: altair (>=5.5.0)
Requires-Dist: matplotlib (>=3.9.3)
Requires-Dist: pandas (>=2.2.3)
Requires-Dist: requests (>=2.32.3)
Requires-Dist: statistics (>=1.0.3.5)
